[
  {
    "id": "069735050e47c22f49d289ca94bbeffedccf885c",
    "title": "Tokenized RWAs climb 13.5% despite $1T crypto market drawdown",
    "url": "https://cointelegraph.com/news/tokenized-rwas-climb-despite-crypto-market-rout",
    "source": "Cointelegraph",
    "firstSeenAt": "2026-02-16T19:27:38.388Z",
    "lastSeenAt": "2026-02-17T15:05:10.017Z",
    "sectionShown": "briefing",
    "topicTags": [
      "tokenized",
      "rwas",
      "climb",
      "despite",
      "crypto",
      "market",
      "drawdown",
      "real"
    ],
    "majorUpdate": false,
    "updateReason": null
  },
  {
    "id": "2c190947e5e5cab8597659ba37a1216bc24179e6",
    "title": "Raydium’s 200% volume spike tests RAY’s breakout strength – Here’s why",
    "url": "https://ambcrypto.com/raydiums-200-volume-spike-tests-rays-breakout-strength-heres-why",
    "source": "AMB Crypto",
    "firstSeenAt": "2026-02-17T15:05:10.016Z",
    "lastSeenAt": "2026-02-17T15:05:10.016Z",
    "sectionShown": "briefing",
    "topicTags": [
      "raydium",
      "volume",
      "spike",
      "tests",
      "breakout",
      "strength",
      "here",
      "strengthens"
    ],
    "majorUpdate": false,
    "updateReason": null
  },
  {
    "id": "0f4b0a5dc496106e5909c5f1ed4e2507dad5b9aa",
    "title": "Crypto Funds See 4th Week of Outflows, but XRP and SOL Shine: CoinShares Report",
    "url": "https://cryptopotato.com/crypto-funds-see-4th-week-of-outflows-but-xrp-and-sol-shine-coinshares-report",
    "source": "CryptoPotato",
    "firstSeenAt": "2026-02-17T15:05:10.016Z",
    "lastSeenAt": "2026-02-17T15:05:10.016Z",
    "sectionShown": "briefing",
    "topicTags": [
      "crypto",
      "funds",
      "week",
      "outflows",
      "shine",
      "coinshares",
      "report",
      "four"
    ],
    "majorUpdate": false,
    "updateReason": null
  },
  {
    "id": "9dd80e4bd869a97fad9d734fd70b5bfcae783b2c",
    "title": "State of Pyth Q4 2025",
    "url": "https://messari.io/article/state-of-pyth-q4-2025",
    "source": "Messari",
    "firstSeenAt": "2026-02-13T18:02:01.173Z",
    "lastSeenAt": "2026-02-16T19:28:44.130Z",
    "sectionShown": "briefing",
    "topicTags": [
      "state",
      "pyth",
      "2025",
      "closed",
      "with",
      "rising",
      "data",
      "throughput"
    ],
    "majorUpdate": false,
    "updateReason": null
  },
  {
    "id": "087f40df787c3a38172764185312321013969b5d",
    "title": "Solana Company shares jump 17% as firm rolls out borrowing against staked SOL",
    "url": "https://www.theblock.co/post/389924/solana-company-shares-17-borrowing-against-staked-sol",
    "source": "The Block",
    "firstSeenAt": "2026-02-14T15:05:50.189Z",
    "lastSeenAt": "2026-02-16T19:28:44.130Z",
    "sectionShown": "briefing",
    "topicTags": [
      "solana",
      "company",
      "shares",
      "jump",
      "firm",
      "rolls",
      "borrowing",
      "against"
    ],
    "majorUpdate": false,
    "updateReason": null
  },
  {
    "id": "d338db71fd51617b7606b67ef7f9cf9f2e98236a",
    "title": "Solana’s RWA ecosystem hits $1.66B – Is this SOL’s turning point?",
    "url": "https://ambcrypto.com/solanas-rwa-ecosystem-hits-1-66b-is-this-sols-turning-point",
    "source": "AMB Crypto",
    "firstSeenAt": "2026-02-16T15:45:27.220Z",
    "lastSeenAt": "2026-02-16T15:45:27.220Z",
    "sectionShown": "briefing",
    "topicTags": [
      "solana",
      "ecosystem",
      "hits",
      "this",
      "turning",
      "point",
      "fundamentals",
      "surges"
    ],
    "majorUpdate": false,
    "updateReason": null
  }
]